verilog/A2/Q1/ALU.v
//Implementing a 1 bit ALU in Verilog
//Suraj Singh 16CO146
//Tarun Anand 16CO147
//Date: 25/10/17

//All the control inputs to the ALU have been specified in the array "control"
//Bits 4 and 3 denote the operation input which controls which function of the ALU is processed 
//Bits 2 denotes Ainvert and Binvert combined 
//Bit 1 represents carry in 
//Bit 0 represents shift left




module ALU(A, B , control, shiftout, out,overflow,iszero,greaterthan);
	input A;
	input B;
	input [4:0] control; 
	output reg out,overflow,iszero,greaterthan;
    output reg [1:0] shiftout;


	always@(control or A or B)
	begin
	case(control[4:3]) //bits 5 and 4 account for which operation
		0: //if operation is 0, then the adder is invoked. it takes A, B and carry in as input
		begin
			out = A^B^control[1];
			overflow = (A^B)&control[1] + A&B;
		end

		1: //if operation is 1, then the subtractor is invoked. it takes A, B and carry(borrow) in as input
		begin
			out = A^B^control[1];
			overflow = (!A)&control[1] + (!(A^B))&control[1];
		end

		2: //if operation is 2, then the AND operation is invoked. If Ainvert and Binvert are 1, then output of ALU is A NAND B. Else, A AND B
		begin
			if(control[2])
				out = (!A) & (!B);
			else
				out = A&B;
		end

		3: //if operation is 3, then the OR operation is invoked. If Ainvert and Binvert are 1, then the ouput of the ALU is A NOR B. Else, A OR B
		begin
			if(control[2])
				out = (!A) | (!B);
			else
				out = A|B;
		end

		default out = 0;
	endcase
    // for the shift left operation 
		if(control[0])
			shiftout  = out<<1;
		else
			shiftout = out;
        if(out==0)  //flag to indicate whetehr the output is zero or not
            iszero =1;
        else
            iszero = 0;

        if(A>B)  //flag to indicate if the first input (A) is greater than the second input (B) or
            greaterthan =1;
        else
            greaterthan = 0;

    end

endmodule

verilog/A2/Q1/ALU_testbench.v
//TESTBENCH for 1 bit ALU
//Suraj Singh 16CO146
//Tarun Anand 16CO147
//Date: 25/10/17


//operation 0 indicates addition
//operation 0 indicates subtraction


module ALU_t;
	reg A;
	reg B;
	reg [4:0] control;
	wire out, overflow,iszero, greaterthan;
    wire [1:0] shiftout;

	ALU M1(A,B,control,shiftout,out,overflow,iszero,greaterthan);
	initial
	begin
		$dumpfile("ALU.vcd");
		$dumpvars(0, ALU_t);

        //bits 4 and 3 are 0, hence addition takes place. carry in is 0 and shift left is true (value of Ainvert Binvert won't even be considered for this operation)
		A = 1'b0;
		B = 1'b1;
		control = 5'b00001;
		#10
        //bits 4 and 3 indicate operation 2 which is AND. since Ainvert and Binvert is 1, NAND happens. Shift left is 0.
        A = 1'b1;
		B = 1'b1;
		control = 5'b10100;
		#10
        //addition with overflow, as carry in is 1
		A = 1'b0;
		B = 1'b1;
		control = 5'b00011;
        #10
        //AND operation
        A = 1'b1;
		B = 1'b0;
		control = 5'b10000;
        #10
        //AND operation
        A = 1'b1;
		B = 1'b1;
		control = 5'b10011;
        #10
        //OR operation
        A = 1'b0;
		B = 1'b1;
		control = 5'b11001;
        #10
        //NOR operation
        A = 1'b1;
		B = 1'b1;
		control = 5'b11010;
		//Subtraction without borrow
        #10
        A = 1'b1;
		B = 1'b0;
		control = 5'b01000;
		#10
		//Subtraction with borrow
		A = 1'b1;
		B = 1'b1;
		control = 5'b01010;
        #10
		$finish;
	end
	initial
		begin
			$monitor("A: %d B: %d Carryin/Borrowin: %d Control Signal: %d Shiftin: %d Output: %d Overflow: %d Shiftout: %2b IsZero? : %d A>B? : %d \n", A,B,control[1], control[4:3], control[0],out,overflow, shiftout, iszero, greaterthan);
		end

endmodule

verilog/A2/Q1/ALU.vcd
$date
	Tue Oct 31 21:32:18 2017
$end
$version
	Icarus Verilog
$end
$timescale
	1s
$end
$scope module ALU_t $end
$var wire 1 ! greaterthan $end
$var wire 1 " iszero $end
$var wire 1 # out $end
$var wire 1 $ overflow $end
$var wire 2 % shiftout [1:0] $end
$var reg 1 & A $end
$var reg 1 ' B $end
$var reg 5 ( control [4:0] $end
$scope module M1 $end
$var wire 1 ) A $end
$var wire 1 * B $end
$var wire 5 + control [4:0] $end
$var reg 1 , greaterthan $end
$var reg 1 - iszero $end
$var reg 1 . out $end
$var reg 1 / overflow $end
$var reg 2 0 shiftout [1:0] $end
$upscope $end
$upscope $end
$enddefinitions $end
#0
$dumpvars
b10 0
0/
1.
0-
0,
b1 +
1*
0)
b1 (
1'
0&
b10 %
0$
1#
0"
0!
$end
#10
1-
1"
b0 0
b0 %
0.
0#
b10100 (
b10100 +
1&
1)
#20
1/
1$
b11 (
b11 +
0&
0)
#30
1,
1!
b10000 (
b10000 +
0'
0*
1&
1)
#40
0,
0!
0-
0"
b10 0
b10 %
1.
1#
b10011 (
b10011 +
1'
1*
#50
b11001 (
b11001 +
0&
0)
#60
b1 0
b1 %
b11010 (
b11010 +
1&
1)
#70
1,
1!
0/
0$
b1000 (
b1000 +
0'
0*
#80
0,
0!
b1010 (
b1010 +
1'
1*
