verilog/16CO146-VB2.v
module othertoBCD(a,b,c,d,w,x,y,z);
	
	
	input a,b,c,d;
	output reg w,x,y,z;
	reg tmp;
	
	always @(a or b or c or d)
		begin

			z = (d);
			y = c&(!d) | (!c)&(d);
			tmp = c | d;
			x = (b)&(!tmp) | (!b)&tmp;
			w = ((a) &  (b|((!c)&(!d))));
		end

endmodule

verilog/testbench1.v
//TESTBENCH for Gate modeling program for converting 84-2-1 to BCD
module othertoBCD_t;

  reg  a, b,c,d;
  //'timescale 1ns/10ps'

  othertoBCD M1 (a,b,c,d,w,x,y,z);

  initial begin
  $dumpfile("fiNal.vcd");
  $dumpvars(0, othertoBCD_t);
    a = 1'b0;
    b = 1'b0;
    c = 1'b0;
    d = 1'b0;
    #100
    a = 1'b0;
    b = 1'b1;
    c = 1'b1;
    d = 1'b1;
    #100
    a = 1'b0;
    b = 1'b1;
    c = 1'b1;
    d = 1'b0;
    #100
    a = 1'b0;
    b = 1'b1;
    c = 1'b0;
    d = 1'b1;
    #100
    a = 1'b0;
    b = 1'b1;
    c = 1'b0;
    d = 1'b0;
    #100
    a = 1'b1;
    b = 1'b0;
    c = 1'b1;
    d = 1'b1;
    #100
    a = 1'b1;
    b = 1'b0;
    c = 1'b1;
    d = 1'b0;
    #100
    a = 1'b1;
    b = 1'b0;
    c = 1'b0;
    d = 1'b1;
    #100
    a = 1'b1;
    b = 1'b0;
    c = 1'b0;
    d = 1'b0;
    #100
    a = 1'b1;
    b = 1'b1;
    c = 1'b1;
    d = 1'b1;
    #100
    $finish;
  end
  //initial #600 finish
endmodule

verilog/FINAL.vcd
$date
	Wed Sep 20 00:02:25 2017
$end
$version
	Icarus Verilog
$end
$timescale
	1s
$end
$scope module othertoBCD_t $end
$var wire 1 ! w $end
$var wire 1 " x $end
$var wire 1 # y $end
$var wire 1 $ z $end
$var reg 1 % a $end
$var reg 1 & b $end
$var reg 1 ' c $end
$var reg 1 ( d $end
$scope module M1 $end
$var wire 1 ) a $end
$var wire 1 * b $end
$var wire 1 + c $end
$var wire 1 , d $end
$var reg 1 - tmp $end
$var reg 1 . w $end
$var reg 1 / x $end
$var reg 1 0 y $end
$var reg 1 1 z $end
$upscope $end
$upscope $end
$enddefinitions $end
#0
$dumpvars
01
00
0/
0.
0-
0,
0+
0*
0)
0(
0'
0&
0%
0$
0#
0"
0!
$end
#100
1/
1"
1-
10
1#
11
1$
1(
1,
#200
01
0$
0(
0,
1'
1+
#300
00
0#
11
1$
1(
1,
#400
0-
01
0$
0(
0,
0'
0+
1&
1*
#500
1.
1!
0/
0"
1-
10
1#
11
1$
1(
1,
#600
01
0$
0(
0,
1'
1+
#700
00
0#
11
1$
1(
1,
#800
0-
01
0$
0(
0,
0'
0+
0&
0*
1%
1)
#900
1/
1"
1-
10
1#
11
1$
1(
1,
