verilog/coa/decoder.v
//Behavioural modeling of a 4:16 Decoder
//16CO146 Suraj Singh
//16CO147 Tarun Anand
//Date: 07/10/2017

module decoder(enable,in,out);
	input enable; 
	input [3:0] in;
	
	output reg [15:0] out;
	always@(in or enable) 
	begin
		out = 0;
		if (enable)
		begin
			case(in)
				4'd0: out= 16'h1;
				4'd1: out= 16'h2;
				4'd2: out= 16'h4;
				4'd3: out= 16'h8;
				4'd4: out= 16'h10;
				4'd5: out= 16'h20;
				4'd6: out= 16'h40;
				4'd7: out= 16'h80;
				4'd8: out= 16'h100;
				4'd9: out= 16'h200;
				4'd10: out= 16'h400;
				4'd11: out= 16'h800;
				4'd12: out= 16'h1000;
				4'd13: out= 16'h2000;
				4'd14: out= 16'h4000;
				4'd15: out= 16'h8000;
			endcase
		end
	end
endmodule

verilog/coa/decoder_testbench.v
//Testbench for a 4:16 Decoder
//16CO146 Suraj Singh
//16C0147 Tarun Anand

module decoder_t;
	reg enable;
	reg [3:0] in;
	wire [15:0] out;
	decoder M1(enable,in,out);
	initial
	begin	
		$dumpfile("A2decoder.vcd");
		$dumpvars(0, decoder_t);
		in= 4'd0;
		enable = 0;
		#100;
		in= 4'd1;
		#100;
		in= 4'd0;
		enable = 1;
		#100;
		in= 4'd1;
		#100;
		in= 4'd2;
		#100; 
		in= 4'd3;
		#100; 
		in= 4'd4;
		#100; 
		in= 4'd5;
		#100;			
		in= 4'd6;
		#100;
		in= 4'd7;
		#100;
		in= 4'd8;
		#100; 
		in= 4'd9;
		#100;
		in= 4'd10;
		#100; 
		in= 4'd11;
		#100; 
		in= 4'd12;
		#100; 
		in= 4'd13;
		#100; 
		in= 4'd14;
		#100; 
		in= 4'd15;
		#100; 
		$finish;
	end
endmodule

verilog/coa/A2decoder.vcd
$date
	Sat Oct  7 11:29:19 2017
$end
$version
	Icarus Verilog
$end
$timescale
	1s
$end
$scope module decoder_t $end
$var wire 16 ! out [15:0] $end
$var reg 1 " enable $end
$var reg 4 # in [3:0] $end
$scope module M1 $end
$var wire 1 $ enable $end
$var wire 4 % in [3:0] $end
$var reg 16 & out [15:0] $end
$upscope $end
$upscope $end
$enddefinitions $end
#0
$dumpvars
b0 &
b0 %
0$
b0 #
0"
b0 !
$end
#100
b1 #
b1 %
#200
b1 &
b1 !
1"
1$
b0 #
b0 %
#300
b10 &
b10 !
b1 #
b1 %
#400
b100 &
b100 !
b10 #
b10 %
#500
b1000 &
b1000 !
b11 #
b11 %
#600
b10000 &
b10000 !
b100 #
b100 %
#700
b100000 &
b100000 !
b101 #
b101 %
#800
b1000000 &
b1000000 !
b110 #
b110 %
#900
b10000000 &
b10000000 !
b111 #
b111 %
#1000
b100000000 &
b100000000 !
b1000 #
b1000 %
#1100
b1000000000 &
b1000000000 !
b1001 #
b1001 %
#1200
b10000000000 &
b10000000000 !
b1010 #
b1010 %
#1300
b100000000000 &
b100000000000 !
b1011 #
b1011 %
#1400
b1000000000000 &
b1000000000000 !
b1100 #
b1100 %
#1500
b10000000000000 &
b10000000000000 !
b1101 #
b1101 %
#1600
b100000000000000 &
b100000000000000 !
b1110 #
b1110 %
#1700
b1000000000000000 &
b1000000000000000 !
b1111 #
b1111 %
